plsc_serving/__init__.py
plsc_serving/run/__init__.py
plsc_serving/server/conf/cube.conf
plsc_serving/server/conf/gflags.conf
plsc_serving/server/conf/model_toolkit.prototxt
plsc_serving/server/conf/model_toolkit.prototxt.0
plsc_serving/server/conf/model_toolkit.prototxt.1
plsc_serving/server/conf/model_toolkit.prototxt.10
plsc_serving/server/conf/model_toolkit.prototxt.11
plsc_serving/server/conf/model_toolkit.prototxt.12
plsc_serving/server/conf/model_toolkit.prototxt.13
plsc_serving/server/conf/model_toolkit.prototxt.14
plsc_serving/server/conf/model_toolkit.prototxt.15
plsc_serving/server/conf/model_toolkit.prototxt.2
plsc_serving/server/conf/model_toolkit.prototxt.3
plsc_serving/server/conf/model_toolkit.prototxt.4
plsc_serving/server/conf/model_toolkit.prototxt.5
plsc_serving/server/conf/model_toolkit.prototxt.6
plsc_serving/server/conf/model_toolkit.prototxt.7
plsc_serving/server/conf/model_toolkit.prototxt.8
plsc_serving/server/conf/model_toolkit.prototxt.9
plsc_serving/server/conf/resource.prototxt
plsc_serving/server/conf/resource.prototxt.0
plsc_serving/server/conf/resource.prototxt.1
plsc_serving/server/conf/resource.prototxt.10
plsc_serving/server/conf/resource.prototxt.11
plsc_serving/server/conf/resource.prototxt.12
plsc_serving/server/conf/resource.prototxt.13
plsc_serving/server/conf/resource.prototxt.14
plsc_serving/server/conf/resource.prototxt.15
plsc_serving/server/conf/resource.prototxt.2
plsc_serving/server/conf/resource.prototxt.3
plsc_serving/server/conf/resource.prototxt.4
plsc_serving/server/conf/resource.prototxt.5
plsc_serving/server/conf/resource.prototxt.6
plsc_serving/server/conf/resource.prototxt.7
plsc_serving/server/conf/resource.prototxt.8
plsc_serving/server/conf/resource.prototxt.9
plsc_serving/server/conf/service.prototxt
plsc_serving/server/conf/workflow.prototxt
plsc_serving/server/data/model/paddle/fluid_reload_flag
plsc_serving/server/data/model/paddle/fluid_time_file
plsc_serving-0.1.6.dist-info/LICENSE
plsc_serving-0.1.6.dist-info/METADATA
plsc_serving-0.1.6.dist-info/WHEEL
plsc_serving-0.1.6.dist-info/top_level.txt
plsc_serving-0.1.6.dist-info/RECORD
