Metadata-Version: 2.1
Name: plsc-serving
Version: 0.1.6
Summary: package for plsc serving
Home-page: https://github.com/PaddlePaddle/PLSC
Author: MRXLT
Author-email: xlt2024@gmail.com
License: UNKNOWN
Platform: UNKNOWN
Classifier: Programming Language :: Python :: 3
Classifier: License :: OSI Approved :: MIT License
Classifier: Operating System :: OS Independent
Requires-Python: >=3.5
